bws_crontab/__init__.py
bws_crontab-0.0.1a0.dist-info/entry_points.txt
bws_crontab-0.0.1a0.dist-info/LICENSE
bws_crontab-0.0.1a0.dist-info/WHEEL
bws_crontab-0.0.1a0.dist-info/METADATA
bws_crontab-0.0.1a0.dist-info/RECORD
